claudeboss/__init__.py
claudeboss/__main__.py
claudeboss/active_detector.py
claudeboss/activity.py
claudeboss/app.py
claudeboss/detail.py
claudeboss/detector.py
claudeboss/session.py
claudeboss/summarizer.py
claudeboss/ui.py
claudeboss-0.1.0.dist-info/METADATA
claudeboss-0.1.0.dist-info/WHEEL
claudeboss-0.1.0.dist-info/entry_points.txt
claudeboss-0.1.0.dist-info/licenses/LICENSE
claudeboss-0.1.0.dist-info/RECORD
