Metadata-Version: 2.4
Name: claudeboss
Version: 0.1.0
Summary: Terminal UI for browsing and managing Claude Code sessions
Project-URL: Homepage, https://github.com/thomcom/claudeboss
Project-URL: Repository, https://github.com/thomcom/claudeboss
Author: Andrew Medworth
License-Expression: MIT
License-File: LICENSE
Keywords: browser,claude,cli,ncurses,session,tui
Classifier: Development Status :: 4 - Beta
Classifier: Environment :: Console :: Curses
Classifier: Intended Audience :: Developers
Classifier: License :: OSI Approved :: MIT License
Classifier: Operating System :: POSIX :: Linux
Classifier: Programming Language :: Python :: 3
Classifier: Programming Language :: Python :: 3.10
Classifier: Programming Language :: Python :: 3.11
Classifier: Programming Language :: Python :: 3.12
Classifier: Topic :: Software Development :: User Interfaces
Classifier: Topic :: Utilities
Requires-Python: >=3.10
